aws_cdk_test_synth/__init__.py
aws_cdk_test_synth/test_synth.py
tests/__init__.py
tests/s3_stack.py
tests/test_s3_stack.py
tests/test_synth.py
aws_cdk_test_synth-0.0.4.dist-info/LICENSE
aws_cdk_test_synth-0.0.4.dist-info/METADATA
aws_cdk_test_synth-0.0.4.dist-info/WHEEL
aws_cdk_test_synth-0.0.4.dist-info/top_level.txt
aws_cdk_test_synth-0.0.4.dist-info/RECORD
