Metadata-Version: 2.1
Name: aws-cdk-test-synth
Version: 0.0.4
Summary: AWS CDK test Synth package
Home-page: https://aws-cdk-test-synth.readthedocs.io/
Author: Alessandra Bilardi
Author-email: alessandra.bilardi@gmail.com
License: UNKNOWN
Project-URL: Source, https://github.com/bilardi/aws-cdk-test-synth
Project-URL: Bug Reports, https://github.com/bilardi/aws-cdk-test-synth/issues
Project-URL: Funding, https://donate.pypi.org
Platform: UNKNOWN
Classifier: Programming Language :: Python :: 3
Classifier: License :: OSI Approved :: MIT License
Classifier: Operating System :: OS Independent
Requires-Python: >=3.6
